srai_telegrambot/__init__.py
srai_telegrambot/command/__init__.py
srai_telegrambot/command/command_base.py
srai_telegrambot/command/command_chat_id.py
srai_telegrambot/command/command_help.py
srai_telegrambot/command/command_image_tag.py
srai_telegrambot/dao_telegram_bot.py
srai_telegrambot/mode/__init__.py
srai_telegrambot/mode/text_mode_base.py
srai_telegrambot/mode/text_mode_default.py
srai_telegrambot/mode/text_mode_gpt.py
srai_telegrambot/mode/text_mode_rag.py
srai_telegrambot/mode/voice_mode_base.py
srai_telegrambot/mode/voice_mode_gpt.py
srai_telegrambot/model/__init__.py
srai_telegrambot/model/chat_message.py
srai_telegrambot/telegram_bot.py
srai_telegrambot/telegram_bot_interface.py
srai_telegrambot/telegram_bot_test.py
srai_telegrambot-0.17.2.dist-info/LICENSE.txt
srai_telegrambot-0.17.2.dist-info/METADATA
srai_telegrambot-0.17.2.dist-info/WHEEL
srai_telegrambot-0.17.2.dist-info/RECORD
