Metadata-Version: 2.1
Name: srai-telegrambot
Version: 0.17.2
Summary: A library that makes it easier to build ai powered telegram bots.
Home-page: https://github.com/southriverai/srai-telegrambot
License: MIT
Keywords: SRAI,TOOLS
Author: Jaap Oosterbroek
Author-email: jaap.oosterbroek@gmail.com
Requires-Python: >=3.10,<4.0
Classifier: License :: OSI Approved :: MIT License
Classifier: Programming Language :: Python :: 3
Classifier: Programming Language :: Python :: 3.10
Classifier: Programming Language :: Python :: 3.11
Classifier: Programming Language :: Python :: 3.12
Requires-Dist: langchain-openai (>=0.1.14,<0.2.0)
Requires-Dist: langchain_community (>=0.2.6,<0.3.0)
Requires-Dist: pypdf (>=4.2.0,<5.0.0)
Requires-Dist: python_telegram_bot (>=13.11,<14.0)
Requires-Dist: srai-openai (>=0.8.2,<0.9.0)
Project-URL: Repository, https://github.com/southriverai/srai-telegrambot
